iduoliao_ml_dev/__init__.py
iduoliao_ml_dev/data/__init__.py
iduoliao_ml_dev/data/data.py
iduoliao_ml_dev/data/dataV2.py
iduoliao_ml_dev/data/worksPersonas.py
iduoliao_ml_dev/dataCenter/__init__.py
iduoliao_ml_dev/dataDispose/__init__.py
iduoliao_ml_dev/dataDispose/subject.py
iduoliao_ml_dev/dataDispose/works.py
iduoliao_ml_dev/dataSave/__init__.py
iduoliao_ml_dev/es/__init__.py
iduoliao_ml_dev/filterPool/__init__.py
iduoliao_ml_dev/filterPool/bftWorks.py
iduoliao_ml_dev/hot/__init__.py
iduoliao_ml_dev/hot/hot.py
iduoliao_ml_dev/ilog/__init__.py
iduoliao_ml_dev/imatrix/__init__.py
iduoliao_ml_dev/itemCF/__init__.py
iduoliao_ml_dev/recommend/__init__.py
iduoliao_ml_dev/test/__init__.py
iduoliao_ml_dev-1.1.100.dist-info/LICENSE
iduoliao_ml_dev-1.1.100.dist-info/METADATA
iduoliao_ml_dev-1.1.100.dist-info/WHEEL
iduoliao_ml_dev-1.1.100.dist-info/top_level.txt
iduoliao_ml_dev-1.1.100.dist-info/RECORD
